piphub.py
piphub-1.0.0.data/scripts/piphub
piphub-1.0.0.dist-info/DESCRIPTION.rst
piphub-1.0.0.dist-info/METADATA
piphub-1.0.0.dist-info/RECORD
piphub-1.0.0.dist-info/WHEEL
piphub-1.0.0.dist-info/metadata.json
