Metadata-Version: 2.0
Name: piphub
Version: 1.0.0
Summary: Shortcuts for installing packages from GitHub
Home-page: http://github.com/minrk/piphub
Author: Min Ragan-Kelley
Author-email: benjaminrk@gmail.com
License: BSD
Download-URL: http://github.com/minrk/piphub/releases
Platform: UNKNOWN
Classifier: License :: OSI Approved :: BSD License
Classifier: Operating System :: MacOS :: MacOS X
Classifier: Programming Language :: Python :: 2
Classifier: Programming Language :: Python :: 2.6
Classifier: Programming Language :: Python :: 2.7
Classifier: Programming Language :: Python :: 3
Classifier: Programming Language :: Python :: 3.2
Classifier: Programming Language :: Python :: 3.3
